funcsim/__init__.py
funcsim/addist.py
funcsim/conversions.py
funcsim/core.py
funcsim/cpt.py
funcsim/cvmdist.py
funcsim/dependence.py
funcsim/distfit.py
funcsim/ecdfgof.py
funcsim/edf.py
funcsim/eut.py
funcsim/imanconover.py
funcsim/kde.py
funcsim/ksdist.py
funcsim/multicore.py
funcsim/nearby.py
funcsim/plotting.py
funcsim/rdarrays.py
funcsim/screen.py
funcsim/shapiro.py
funcsim/shrinkage.py
funcsim/testsim.py
funcsim/utests.py
funcsim/vect.py
funcsim-0.1.20.dist-info/licenses/LICENSE
tests/__init__.py
tests/test_GBM.py
tests/test_GBM_draw-stdnorm.py
tests/test_GBM_zero-draws.py
tests/test_addist.py
tests/test_conversions.py
tests/test_copula.py
tests/test_covtocorr.py
tests/test_cpt.py
tests/test_cvmdist.py
tests/test_ecdfgof.py
tests/test_edf.py
tests/test_hist_not_data.py
tests/test_imanconover.py
tests/test_indirect_next.py
tests/test_joint_norm.py
tests/test_kde.py
tests/test_ksdist.py
tests/test_nearbypd.py
tests/test_rdarrays.py
tests/test_recdyn_with_no_data0.py
tests/test_shrink.py
tests/test_spearman.py
tests/test_static.py
tests/test_static_zero-draws.py
tests/test_superfluous_data0.py
tests/test_testsim.py
tests/test_utests.py
tests/test_vect.py
tests/test_zzz_compare.py
funcsim-0.1.20.dist-info/METADATA
funcsim-0.1.20.dist-info/WHEEL
funcsim-0.1.20.dist-info/top_level.txt
funcsim-0.1.20.dist-info/RECORD
